LICENSE
MANIFEST.in
README.rst
pyproject.toml
setup.py
src/django_rapyd_wiretap.egg-info/PKG-INFO
src/django_rapyd_wiretap.egg-info/SOURCES.txt
src/django_rapyd_wiretap.egg-info/dependency_links.txt
src/django_rapyd_wiretap.egg-info/requires.txt
src/django_rapyd_wiretap.egg-info/top_level.txt
src/wiretap/__init__.py
src/wiretap/admin.py
src/wiretap/apps.py
src/wiretap/middleware.py
src/wiretap/models.py
src/wiretap/tests.py
src/wiretap/views.py
src/wiretap/migrations/0001_initial.py
src/wiretap/migrations/__init__.py