Metadata-Version: 1.1
Name: django-rapyd-wiretap
Version: 0.0.3
Summary: Logs requests and responses to your application in a DB for auditing or troubleshooting purposes.
Home-page: https://github.com/karthicraghupathi/django_rapyd_wiretap_project
Author: Karthic Raghupathi
Author-email: karthicr@gmail.com
License:                                  Apache License
